ezsync/__init__.py
ezsync-0.1.0.dist-info/LICENSE
ezsync-0.1.0.dist-info/METADATA
ezsync-0.1.0.dist-info/WHEEL
ezsync-0.1.0.dist-info/top_level.txt
ezsync-0.1.0.dist-info/RECORD
